sunhpcSnack/__init__.py
sunhpcSnack/_snack.so
sunhpcSnack/snack.py
sunhpcSnack-1.0.0.dist-info/METADATA
sunhpcSnack-1.0.0.dist-info/WHEEL
sunhpcSnack-1.0.0.dist-info/top_level.txt
sunhpcSnack-1.0.0.dist-info/RECORD
